pycol/Collector.py
pycol/__init__.py
pycol/util.py
pycol-0.1.0.dist-info/LICENSE
pycol-0.1.0.dist-info/METADATA
pycol-0.1.0.dist-info/WHEEL
pycol-0.1.0.dist-info/top_level.txt
pycol-0.1.0.dist-info/RECORD
